[
  {
    "kind": "customsearch#result",
    "title": "Corporate Responsibility Report 2019",
    "htmlTitle": "Corporate Responsibility Report <b>2019</b>",
    "link": "https://www.credit-suisse.com/media/assets/corporate/docs/about-us/investor-relations/financial-disclosures/financial-reports/csg-crr-2019-en.pdf",
    "displayLink": "www.credit-suisse.com",
    "snippet": "of 2019, Credit Suisse had over CHF 44 billion of assets invested according to sustainability criteria. Another important step was the announcement in.",
    "htmlSnippet": "of <b>2019</b>, Credit Suisse had over CHF 44 billion of assets invested according to <b>sustainability</b> criteria. Another important step was the announcement in.",
    "formattedUrl": "https://www.credit-suisse.com/media/assets/...us/.../csg-crr-2019-en.pdf",
    "htmlFormattedUrl": "https://www.credit-suisse.com/media/assets/...us/.../csg-crr-<b>2019</b>-en.pdf",
    "pagemap": {
      "cse_thumbnail": [
        {
          "src": "https://encrypted-tbn0.gstatic.com/images?q=tbn:ANd9GcTWLixbzv447vNngpFdABhsimjpxm-7XpRLsaJBvjpmxjZMrIUsvINYhB4",
          "width": "261",
          "height": "193"
        }
      ],
      "metatags": [
        {
          "moddate": "D:20200803094902+02'00'",
          "creationdate": "D:20200403132218+02'00'",
          "creator": "e-reporting",
          "author": "Credit Suisse Group AG",
          "subject": "Corporate Responsibility Report 2019",
          "producer": "Adobe PDF Library 10.0.1",
          "title": "Corporate Responsibility Report 2019"
        }
      ],
      "cse_image": [
        {
          "src": "x-raw-image:///71f87aba232f9af8520f53d4558c1af0efd63f4302a1ff7651defe7f2f77ebbf"
        }
      ]
    },
    "mime": "application/pdf",
    "fileFormat": "PDF/Adobe Acrobat"
  },
  {
    "kind": "customsearch#result",
    "title": "Second Party Opinion from ISS-oekom 2019",
    "htmlTitle": "Second Party Opinion from ISS-oekom <b>2019</b>",
    "link": "https://www.credit-suisse.com/media/assets/about-us/docs/investor-relations/debt-investors/green-bonds/190222-second-party-opinion-from-iss-oekom.pdf",
    "displayLink": "www.credit-suisse.com",
    "snippet": "SECON PARTY OPINION (SPO). Sustainability Quality of the Issuer and Green Finance Asset Pool. Credit Suisse. 12 June 2019 ...",
    "htmlSnippet": "SECON PARTY OPINION (SPO). <b>Sustainability</b> Quality of the Issuer and Green Finance Asset Pool. Credit Suisse. 12 June <b>2019</b>&nbsp;...",
    "formattedUrl": "https://www.credit-suisse.com/.../190222-second-party-opinion-from-iss- oekom.pdf",
    "htmlFormattedUrl": "https://www.credit-suisse.com/.../190222-second-party-opinion-from-iss- oekom.pdf",
    "pagemap": {
      "cse_thumbnail": [
        {
          "src": "https://encrypted-tbn1.gstatic.com/images?q=tbn:ANd9GcST4AtFQHtHC1-ivkmj8HJ9uEk0vK_qbJcXI0vkC5eBXcknPdivnAc4xZf4",
          "width": "288",
          "height": "175"
        }
      ],
      "metatags": [
        {
          "moddate": "D:20200510174243+02'00'",
          "creationdate": "D:20190612113006+01'00'",
          "creator": "PDFescape Online - https://www.pdfescape.com",
          "author": "ISS-oekom",
          "subject": "Second Party Opinion from ISS-oekom 2019",
          "producer": "RAD PDF 3.9.6.0 - https://www.radpdf.com",
          "title": "Second Party Opinion from ISS-oekom 2019"
        }
      ],
      "cse_image": [
        {
          "src": "x-raw-image:///b2bea2d2e981e045a08601f4af3aefb6489164514b432d4211d4b287a2a34cd9"
        }
      ]
    },
    "mime": "application/pdf",
    "fileFormat": "PDF/Adobe Acrobat"
  },
  {
    "kind": "customsearch#result",
    "title": "credit-suisse-gri-content-index-2019.pdf",
    "htmlTitle": "credit-suisse-gri-content-index-<b>2019</b>.pdf",
    "link": "https://www.credit-suisse.com/media/assets/corporate/docs/about-us/responsibility/approach-reporting/credit-suisse-gri-content-index-2019.pdf",
    "displayLink": "www.credit-suisse.com",
    "snippet": "Credit Suisse used the GRI Standards for sustainability reporting. (core option) in the development of its corporate responsibility reporting.",
    "htmlSnippet": "Credit Suisse used the GRI Standards for <b>sustainability</b> reporting. (core option) in the development of its corporate responsibility reporting.",
    "cacheId": "0IbuOVxvz1gJ",
    "formattedUrl": "https://www.credit-suisse.com/.../credit-suisse-gri-content-index-2019.pdf",
    "htmlFormattedUrl": "https://www.credit-suisse.com/.../credit-suisse-gri-content-index-<b>2019</b>.pdf",
    "pagemap": {
      "cse_thumbnail": [
        {
          "src": "https://encrypted-tbn0.gstatic.com/images?q=tbn:ANd9GcSLK1vo-AS06bn7Qe6FM9RVNmNVcpHNNk8wkjzujjb6QEISDvR8U_5Auoo",
          "width": "189",
          "height": "267"
        }
      ],
      "metatags": [
        {
          "si_data": "DataClass%2b9d401f75-6608-41d3-bd1f-efe1542cdc01=I%3d9d401f75-6608-41d3-bd1f-efe1542cdc01%26N%3dConfidential%26V%3d1.3%26U%3dS-1-5-21-3718294971-3193642644-4012788348-28095%26D%3dBurri%252c%2bPatrik%2b(MCRC%2b22)%26A%3dAssociated%26H%3dFalse",
          "moddate": "D:20200415141800+02'00'",
          "creator": "Aspose Ltd.",
          "creationdate": "D:20200415141800+02'00'",
          "author": "Michniewicz, Piotr J. (MCIZ 134)",
          "producer": "Aspose.Pdf for .NET 10.9.0",
          "classification": "Confidential"
        }
      ],
      "cse_image": [
        {
          "src": "x-raw-image:///f9c1d9e8f573c84c2438e4dee0cf083c54ef588fb8638058a06778566a820df1"
        }
      ]
    },
    "mime": "application/pdf",
    "fileFormat": "PDF/Adobe Acrobat"
  },
  {
    "kind": "customsearch#result",
    "title": "Second Party Opinion from ISS-​ESG 2020",
    "htmlTitle": "Second Party Opinion from ISS-​ESG 2020",
    "link": "https://www.credit-suisse.com/media/assets/about-us/docs/investor-relations/debt-investors/green-bonds/200508-second-party-opinion-from-iss-esg.pdf",
    "displayLink": "www.credit-suisse.com",
    "snippet": "May 8, 2020 ... Sustainability Quality of the Issuer and Green Finance Asset Pool ... 2019. 2020. ESG Corporate Rating / Last Modification: 2020-03-18.",
    "htmlSnippet": "May 8, 2020 <b>...</b> <b>Sustainability</b> Quality of the Issuer and Green Finance Asset Pool ... <b>2019</b>. 2020. ESG Corporate Rating / Last Modification: 2020-03-18.",
    "formattedUrl": "https://www.credit-suisse.com/.../200508-second-party-opinion-from-iss-esg. pdf",
    "htmlFormattedUrl": "https://www.credit-suisse.com/.../200508-second-party-opinion-from-iss-esg. pdf",
    "pagemap": {
      "cse_thumbnail": [
        {
          "src": "https://encrypted-tbn0.gstatic.com/images?q=tbn:ANd9GcRZBF6WhV4c4MZO3c9TBT3X3Hh-4LWEg2691ePsmowaP4DBZuqbv1rzNU0",
          "width": "178",
          "height": "282"
        }
      ],
      "metatags": [
        {
          "moddate": "D:20200511113919+02'00'",
          "creationdate": "D:20200511101430+01'00'",
          "creator": "PDFescape Online - https://www.pdfescape.com",
          "author": "Credit Suisse Group AG",
          "subject": "Second Party Opinion (SPO)",
          "producer": "RAD PDF 3.13.6.20 - https://www.radpdf.com",
          "title": "Second Party Opinion (SPO)"
        }
      ],
      "cse_image": [
        {
          "src": "x-raw-image:///1c00d6ee1b9883d0e59b3f6a5b0aaf00fd87d3b97acd4934d2b5fc14f7245f4f"
        }
      ]
    },
    "mime": "application/pdf",
    "fileFormat": "PDF/Adobe Acrobat"
  },
  {
    "kind": "customsearch#result",
    "title": "Corporate Responsibility – At a glance 2019",
    "htmlTitle": "Corporate Responsibility – At a glance <b>2019</b>",
    "link": "https://www.credit-suisse.com/media/assets/corporate/docs/about-us/investor-relations/financial-disclosures/financial-reports/csg-crr-2019-at-a-glance-en.pdf",
    "displayLink": "www.credit-suisse.com",
    "snippet": "Credit Suisse had over CHF 44 billion of assets invested according to sustainability criteria by end-2019. Beyond banking, we help to address challenges facing.",
    "htmlSnippet": "Credit Suisse had over CHF 44 billion of assets invested according to <b>sustainability</b> criteria by end-<b>2019</b>. Beyond banking, we help to address challenges facing.",
    "formattedUrl": "https://www.credit-suisse.com/media/.../csg-crr-2019-at-a-glance-en.pdf",
    "htmlFormattedUrl": "https://www.credit-suisse.com/media/.../csg-crr-<b>2019</b>-at-a-glance-en.pdf",
    "pagemap": {
      "cse_thumbnail": [
        {
          "src": "https://encrypted-tbn2.gstatic.com/images?q=tbn:ANd9GcQUizvbXtowJ7tfTJonREmZhl8M382qb1q-3JfQZMnyf8w-CPZUYWncA15C",
          "width": "261",
          "height": "193"
        }
      ],
      "metatags": [
        {
          "moddate": "D:20200728150538+02'00'",
          "creationdate": "D:20200728113251+02'00'",
          "creator": "Adobe InDesign 15.0 (Macintosh)",
          "author": "Credit Suisse Group AG",
          "subject": "Corporate Responsibility – At a glance 2019",
          "producer": "Adobe PDF Library 15.0",
          "title": "Corporate Responsibility – At a glance 2019"
        }
      ],
      "cse_image": [
        {
          "src": "x-raw-image:///a72e9c7cc697a572b2ffff76280ecc9ffa97766de2547c5a2b8ffb28bf8b75fd"
        }
      ]
    },
    "mime": "application/pdf",
    "fileFormat": "PDF/Adobe Acrobat"
  },
  {
    "kind": "customsearch#result",
    "title": "Making an Impact: Earning Returns on Sustainable Terms",
    "htmlTitle": "Making an Impact: Earning Returns on <b>Sustainable</b> Terms",
    "link": "https://www.credit-suisse.com/media/assets/microsite/docs/corporate-insights/corporate-insights-q2-2019.pdf",
    "displayLink": "www.credit-suisse.com",
    "snippet": "the 2019 U.S. proxy season demonstrates the relevance of ESG as a central topic at shareholder meetings, as environmental issues were among the.",
    "htmlSnippet": "the <b>2019</b> U.S. proxy season demonstrates the relevance of ESG as a central topic at shareholder meetings, as <b>environmental</b> issues were among the.",
    "cacheId": "ZOCH9_uuh3sJ",
    "formattedUrl": "https://www.credit-suisse.com/media/.../corporate-insights-q2-2019.pdf",
    "htmlFormattedUrl": "https://www.credit-suisse.com/media/.../corporate-insights-q2-<b>2019</b>.pdf",
    "pagemap": {
      "cse_thumbnail": [
        {
          "src": "https://encrypted-tbn0.gstatic.com/images?q=tbn:ANd9GcQUaTwAksO9cOyQAdQvrvYIu9hx9IvvQDZmKm1GjqPC7B-lcePi55kXRcw",
          "width": "259",
          "height": "194"
        }
      ],
      "metatags": [
        {
          "moddate": "D:20190624162836-04'00'",
          "creationdate": "D:20190612111606-07'00'",
          "creator": "Adobe InDesign CC 13.1 (Windows)",
          "producer": "Adobe PDF Library 15.0"
        }
      ],
      "cse_image": [
        {
          "src": "x-raw-image:///480bc4c5ce9feff091ce64cea187e30a6ca80a736fec69db632323977ef7a05e"
        }
      ]
    },
    "mime": "application/pdf",
    "fileFormat": "PDF/Adobe Acrobat"
  },
  {
    "kind": "customsearch#result",
    "title": "Credit Suisse Statement on Sustainability",
    "htmlTitle": "Credit Suisse Statement on <b>Sustainability</b>",
    "link": "https://www.credit-suisse.com/media/assets/corporate/docs/about-us/investor-relations/financial-disclosures/financial-reports/sustainability-statement-en.pdf",
    "displayLink": "www.credit-suisse.com",
    "snippet": "2. Mission statement. 3. 3. Sustainability governance. 3. 4. Stakeholder engagement. 4. 5. Environmental management. 4. 6. Products and services.",
    "htmlSnippet": "2. Mission statement. 3. 3. <b>Sustainability</b> governance. 3. 4. Stakeholder engagement. 4. 5. <b>Environmental</b> management. 4. 6. Products and services.",
    "cacheId": "rU2zbq3MWlgJ",
    "formattedUrl": "https://www.credit-suisse.com/media/.../sustainability-statement-en.pdf",
    "htmlFormattedUrl": "https://www.credit-suisse.com/media/.../<b>sustainability</b>-statement-en.pdf",
    "pagemap": {
      "cse_thumbnail": [
        {
          "src": "https://encrypted-tbn2.gstatic.com/images?q=tbn:ANd9GcQPjJGECrfr4Hp_gpnBHSb7fw5gbhn9ANCzxRCagBVZA8LVYzD6h7uBea4",
          "width": "265",
          "height": "190"
        }
      ],
      "metatags": [
        {
          "si_data": "DataClass%2b5e2ccede-aa3d-4eba-b8ed-43e293c7fd2e=I%3d5e2ccede-aa3d-4eba-b8ed-43e293c7fd2e%26N%3dInternal%26V%3d1.3%26U%3dS-1-5-21-2278521704-3980307904-2497600207-98787%26D%3dWanat%252c%2bMonika%2b(MCIZ%2b33)%26A%3dAssociated%26H%3dFalse",
          "moddate": "D:20190204104645+01'00'",
          "creationdate": "D:20190204104638+01'00'",
          "creator": "Aspose Ltd.",
          "sourcemodified": "D:20190201141905",
          "_siprop12dataclass_5e2ccede_aa3d_4eba_b8ed_43e293c7fd2e": "v=1.2>I=5e2ccede-aa3d-4eba-b8ed-43e293c7fd2e&N=Internal&V=1.3&U=S-1-5-21-2278521704-3980307904-2497600207-98787&D=Wanat%2c+Monika+(MCIZ+33)&A=Associated&H=False",
          "author": "Wanat, Monika (SOEW 151)",
          "producer": "Aspose.Pdf for .NET 10.9.0",
          "company": "Credit Suisse",
          "classification": "Internal",
          "contenttypeid": "0x0101005232940C6D63F644875D7E3A71A65777"
        }
      ],
      "cse_image": [
        {
          "src": "x-raw-image:///9b5bee7a84cfe242a08005b428517fdeeaef3c6cfde9764b9d5a49d8adcc126b"
        }
      ]
    },
    "mime": "application/pdf",
    "fileFormat": "PDF/Adobe Acrobat"
  },
  {
    "kind": "customsearch#result",
    "title": "SGS Assurance Statement for 2019 Reporting",
    "htmlTitle": "SGS Assurance Statement for <b>2019</b> Reporting",
    "link": "https://www.credit-suisse.com/media/assets/corporate/docs/about-us/responsibility/approach-reporting/sgs-assurance-statement-en.pdf",
    "displayLink": "www.credit-suisse.com",
    "snippet": "corporate responsibility 2019 published at www.credit-suisse.com/responsibility. The scope of the assurance, based on the «SGS. Sustainability Report ...",
    "htmlSnippet": "corporate responsibility <b>2019</b> published at www.credit-suisse.com/responsibility. The scope of the assurance, based on the «SGS. <b>Sustainability</b> Report&nbsp;...",
    "cacheId": "lwJ7mUX2LR8J",
    "formattedUrl": "https://www.credit-suisse.com/media/.../sgs-assurance-statement-en.pdf",
    "htmlFormattedUrl": "https://www.credit-suisse.com/media/.../sgs-assurance-statement-en.pdf",
    "pagemap": {
      "cse_thumbnail": [
        {
          "src": "https://encrypted-tbn2.gstatic.com/images?q=tbn:ANd9GcQcUKag2zZXV4ia6cyHa5sVlPqjRL9zMdnEZp3ehPia7nTaqezsSOhpnMmn",
          "width": "330",
          "height": "153"
        }
      ],
      "metatags": [
        {
          "moddate": "D:20200421155626+02'00'",
          "creator": "Microsoft® Word for Office 365",
          "creationdate": "D:20200421155626+02'00'",
          "author": "template_user",
          "producer": "Microsoft® Word for Office 365"
        }
      ],
      "cse_image": [
        {
          "src": "x-raw-image:///ea7634d9f1c2e466a00f92f78c5aaed39f8c42e58d126753b2a107aabc3e6888"
        }
      ]
    },
    "mime": "application/pdf",
    "fileFormat": "PDF/Adobe Acrobat"
  },
  {
    "kind": "customsearch#result",
    "title": "Full year and fourth quarter 2019 financial results",
    "htmlTitle": "Full year and fourth quarter <b>2019</b> financial results",
    "link": "https://www.credit-suisse.com/media/assets/corporate/docs/about-us/media/media-release/2020/02/q4-19-press-release-en.pdf",
    "displayLink": "www.credit-suisse.com",
    "snippet": "Feb 13, 2020 ... “When I joined Credit Suisse in 2015, we initiated a deep, three year-long restructuring programme, with the intention of creating sustainable ...",
    "htmlSnippet": "Feb 13, 2020 <b>...</b> “When I joined Credit Suisse in 2015, we initiated a deep, three year-long restructuring programme, with the intention of creating <b>sustainable</b>&nbsp;...",
    "formattedUrl": "https://www.credit-suisse.com/media/assets/.../q4-19-press-release-en.pdf",
    "htmlFormattedUrl": "https://www.credit-suisse.com/media/assets/.../q4-19-press-release-en.pdf",
    "pagemap": {
      "cse_thumbnail": [
        {
          "src": "https://encrypted-tbn1.gstatic.com/images?q=tbn:ANd9GcSum6TDyibeyEZsFzoqy5a8Kpm0woyYp2mPJkZ64NkmoLt_u59soMsQ1JEm",
          "width": "189",
          "height": "267"
        }
      ],
      "metatags": [
        {
          "moddate": "D:20200213005921+01'00'",
          "creationdate": "D:20200212214626Z",
          "creator": "Microsoft® Word 2016",
          "author": "Credit Suisse Group AG",
          "subject": "Full year and fourth quarter 2019 financial results",
          "producer": "Microsoft® Word 2016",
          "title": "Full year and fourth quarter 2019 financial results"
        }
      ],
      "cse_image": [
        {
          "src": "x-raw-image:///05ce170cae8970dddd103c9bbc3e4e6a21deb3662447268c3da583da22bc8c12"
        }
      ]
    },
    "mime": "application/pdf",
    "fileFormat": "PDF/Adobe Acrobat"
  },
  {
    "kind": "customsearch#result",
    "title": "Sustainable Finance Disclosure Regulation Financial Market ...",
    "htmlTitle": "<b>Sustainable</b> Finance Disclosure Regulation Financial Market ...",
    "link": "https://www.credit-suisse.com/media/assets/microsite/docs/multiconcept/mcfm-entity-level-disclosure-esg-sfdr.pdf",
    "displayLink": "www.credit-suisse.com",
    "snippet": "Transparency of sustainability risk policies. Pursuant to EU Regulation (EU) 2019/2088 of the European Parliament and of the Council of 27 November 2019 on.",
    "htmlSnippet": "Transparency of <b>sustainability</b> risk policies. Pursuant to EU Regulation (EU) <b>2019</b>/2088 of the European Parliament and of the Council of 27 November <b>2019</b> on.",
    "cacheId": "JulQWQlAWjEJ",
    "formattedUrl": "https://www.credit-suisse.com/.../mcfm-entity-level-disclosure-esg-sfdr.pdf",
    "htmlFormattedUrl": "https://www.credit-suisse.com/.../mcfm-entity-level-disclosure-esg-sfdr.pdf",
    "pagemap": {
      "cse_thumbnail": [
        {
          "src": "https://encrypted-tbn3.gstatic.com/images?q=tbn:ANd9GcSwtijPiINCEt2YSzI8HxVYIkFOdQubbxAt2j5CHBduJ1HZin8Pwff-MMU",
          "width": "189",
          "height": "267"
        }
      ],
      "metatags": [
        {
          "moddate": "D:20210309130231+01'00'",
          "creationdate": "D:20210309122251+01'00'",
          "creator": "Microsoft® Word 2016",
          "author": "M784656",
          "producer": "Microsoft® Word 2016",
          "title": "Sustainable Finance Disclosure Regulation Financial Market Participant disclosure of MultiConcept Fund Management S.A."
        }
      ],
      "cse_image": [
        {
          "src": "x-raw-image:///0ba649a713799893cc6b1d163138b3613f188de7ce5b6ace468b871295215982"
        }
      ]
    },
    "mime": "application/pdf",
    "fileFormat": "PDF/Adobe Acrobat"
  }
]